{
  "Defaults": {},
  "Thresholding_rtl_0": {
    "PE": 1,
    "runtime_writeable_weights": 0,
    "depth_trigger_uram": 0,
    "depth_trigger_bram": 0,
    "inFIFODepths": [
      2
    ],
    "outFIFODepths": [
      2
    ],
    "slr": -1
  },
  "FMPadding_rtl_0": {
    "SIMD": 1,
    "inFIFODepths": [
      2
    ],
    "outFIFODepths": [
      2
    ],
    "slr": -1
  },
  "ConvolutionInputGenerator_rtl_0": {
    "SIMD": 1,
    "parallel_window": 0,
    "ram_style": "distributed",
    "inFIFODepths": [
      2
    ],
    "outFIFODepths": [
      2
    ],
    "slr": -1
  },
  "MVAU_rtl_0": {
    "PE": 1,
    "SIMD": 27,
    "ram_style": "auto",
    "resType": "auto",
    "mem_mode": "internal_decoupled",
    "runtime_writeable_weights": 0,
    "inFIFODepths": [
      2
    ],
    "outFIFODepths": [
      2
    ],
    "slr": -1
  },
  "Thresholding_rtl_1": {
    "PE": 1,
    "runtime_writeable_weights": 0,
    "depth_trigger_uram": 0,
    "depth_trigger_bram": 0,
    "inFIFODepths": [
      2
    ],
    "outFIFODepths": [
      2
    ],
    "slr": -1
  },
  "DuplicateStreams_hls_0": {
    "PE": 1,
    "inFIFODepths": [
      2
    ],
    "outFIFODepths": [
      2,
      2
    ],
    "slr": -1
  },
  "MVAU_hls_0": {
    "PE": 1,
    "SIMD": 64,
    "ram_style": "auto",
    "resType": "auto",
    "mem_mode": "internal_decoupled",
    "runtime_writeable_weights": 0,
    "inFIFODepths": [
      2
    ],
    "outFIFODepths": [
      2
    ],
    "slr": -1
  },
  "MVAU_hls_1": {
    "PE": 4,
    "SIMD": 64,
    "ram_style": "auto",
    "resType": "dsp",
    "mem_mode": "internal_decoupled",
    "runtime_writeable_weights": 0,
    "inFIFODepths": [
      2
    ],
    "outFIFODepths": [
      2
    ],
    "slr": -1
  },
  "Thresholding_rtl_2": {
    "PE": 4,
    "runtime_writeable_weights": 0,
    "depth_trigger_uram": 0,
    "depth_trigger_bram": 0,
    "inFIFODepths": [
      2
    ],
    "outFIFODepths": [
      2
    ],
    "slr": -1
  },
  "Thresholding_rtl_3": {
    "PE": 1,
    "runtime_writeable_weights": 0,
    "depth_trigger_uram": 0,
    "depth_trigger_bram": 0,
    "inFIFODepths": [
      2
    ],
    "outFIFODepths": [
      2
    ],
    "slr": -1
  },
  "FMPadding_rtl_1": {
    "SIMD": 1,
    "inFIFODepths": [
      2
    ],
    "outFIFODepths": [
      2
    ],
    "slr": -1
  },
  "ConvolutionInputGenerator_rtl_1": {
    "SIMD": 8,
    "parallel_window": 0,
    "ram_style": "distributed",
    "inFIFODepths": [
      2
    ],
    "outFIFODepths": [
      2
    ],
    "slr": -1
  },
  "MVAU_hls_2": {
    "PE": 1,
    "SIMD": 576,
    "ram_style": "auto",
    "resType": "dsp",
    "mem_mode": "internal_decoupled",
    "runtime_writeable_weights": 0,
    "inFIFODepths": [
      2
    ],
    "outFIFODepths": [
      2
    ],
    "slr": -1
  },
  "Thresholding_rtl_4": {
    "PE": 1,
    "runtime_writeable_weights": 0,
    "depth_trigger_uram": 0,
    "depth_trigger_bram": 0,
    "inFIFODepths": [
      2
    ],
    "outFIFODepths": [
      2
    ],
    "slr": -1
  },
  "MVAU_hls_3": {
    "PE": 4,
    "SIMD": 64,
    "ram_style": "auto",
    "resType": "dsp",
    "mem_mode": "internal_decoupled",
    "runtime_writeable_weights": 0,
    "inFIFODepths": [
      2
    ],
    "outFIFODepths": [
      2
    ],
    "slr": -1
  },
  "Thresholding_rtl_5": {
    "PE": 4,
    "runtime_writeable_weights": 0,
    "depth_trigger_uram": 0,
    "depth_trigger_bram": 0,
    "inFIFODepths": [
      2
    ],
    "outFIFODepths": [
      2
    ],
    "slr": -1
  },
  "AddStreams_hls_0": {
    "PE": 4,
    "inFIFODepths": [
      2,
      2
    ],
    "outFIFODepths": [
      2
    ],
    "slr": -1
  },
  "Thresholding_rtl_6": {
    "PE": 4,
    "runtime_writeable_weights": 0,
    "depth_trigger_uram": 0,
    "depth_trigger_bram": 0,
    "inFIFODepths": [
      2
    ],
    "outFIFODepths": [
      2
    ],
    "slr": -1
  },
  "DuplicateStreams_hls_1": {
    "PE": 4,
    "inFIFODepths": [
      2
    ],
    "outFIFODepths": [
      2,
      2
    ],
    "slr": -1
  },
  "MVAU_hls_4": {
    "PE": 1,
    "SIMD": 256,
    "ram_style": "auto",
    "resType": "auto",
    "mem_mode": "internal_decoupled",
    "runtime_writeable_weights": 0,
    "inFIFODepths": [
      2
    ],
    "outFIFODepths": [
      2
    ],
    "slr": -1
  },
  "Thresholding_rtl_7": {
    "PE": 4,
    "runtime_writeable_weights": 0,
    "depth_trigger_uram": 0,
    "depth_trigger_bram": 0,
    "inFIFODepths": [
      2
    ],
    "outFIFODepths": [
      2
    ],
    "slr": -1
  },
  "Thresholding_rtl_8": {
    "PE": 1,
    "runtime_writeable_weights": 0,
    "depth_trigger_uram": 0,
    "depth_trigger_bram": 0,
    "inFIFODepths": [
      2
    ],
    "outFIFODepths": [
      2
    ],
    "slr": -1
  },
  "FMPadding_rtl_2": {
    "SIMD": 1,
    "inFIFODepths": [
      2
    ],
    "outFIFODepths": [
      2
    ],
    "slr": -1
  },
  "ConvolutionInputGenerator_rtl_2": {
    "SIMD": 8,
    "parallel_window": 0,
    "ram_style": "distributed",
    "inFIFODepths": [
      2
    ],
    "outFIFODepths": [
      2
    ],
    "slr": -1
  },
  "MVAU_hls_5": {
    "PE": 1,
    "SIMD": 576,
    "ram_style": "auto",
    "resType": "dsp",
    "mem_mode": "internal_decoupled",
    "runtime_writeable_weights": 0,
    "inFIFODepths": [
      2
    ],
    "outFIFODepths": [
      2
    ],
    "slr": -1
  },
  "Thresholding_rtl_9": {
    "PE": 1,
    "runtime_writeable_weights": 0,
    "depth_trigger_uram": 0,
    "depth_trigger_bram": 0,
    "inFIFODepths": [
      2
    ],
    "outFIFODepths": [
      2
    ],
    "slr": -1
  },
  "MVAU_hls_6": {
    "PE": 4,
    "SIMD": 64,
    "ram_style": "auto",
    "resType": "auto",
    "mem_mode": "internal_decoupled",
    "runtime_writeable_weights": 0,
    "inFIFODepths": [
      2
    ],
    "outFIFODepths": [
      2
    ],
    "slr": -1
  },
  "Thresholding_rtl_10": {
    "PE": 4,
    "runtime_writeable_weights": 0,
    "depth_trigger_uram": 0,
    "depth_trigger_bram": 0,
    "inFIFODepths": [
      2
    ],
    "outFIFODepths": [
      2
    ],
    "slr": -1
  },
  "AddStreams_hls_1": {
    "PE": 4,
    "inFIFODepths": [
      2,
      2
    ],
    "outFIFODepths": [
      2
    ],
    "slr": -1
  },
  "Thresholding_rtl_11": {
    "PE": 4,
    "runtime_writeable_weights": 0,
    "depth_trigger_uram": 0,
    "depth_trigger_bram": 0,
    "inFIFODepths": [
      2
    ],
    "outFIFODepths": [
      2
    ],
    "slr": -1
  },
  "DuplicateStreams_hls_2": {
    "PE": 4,
    "inFIFODepths": [
      2
    ],
    "outFIFODepths": [
      2,
      2
    ],
    "slr": -1
  },
  "MVAU_hls_7": {
    "PE": 1,
    "SIMD": 256,
    "ram_style": "auto",
    "resType": "auto",
    "mem_mode": "internal_decoupled",
    "runtime_writeable_weights": 0,
    "inFIFODepths": [
      2
    ],
    "outFIFODepths": [
      2
    ],
    "slr": -1
  },
  "Thresholding_rtl_12": {
    "PE": 4,
    "runtime_writeable_weights": 0,
    "depth_trigger_uram": 0,
    "depth_trigger_bram": 0,
    "inFIFODepths": [
      2
    ],
    "outFIFODepths": [
      2
    ],
    "slr": -1
  },
  "Thresholding_rtl_13": {
    "PE": 1,
    "runtime_writeable_weights": 0,
    "depth_trigger_uram": 0,
    "depth_trigger_bram": 0,
    "inFIFODepths": [
      2
    ],
    "outFIFODepths": [
      2
    ],
    "slr": -1
  },
  "FMPadding_rtl_3": {
    "SIMD": 1,
    "inFIFODepths": [
      2
    ],
    "outFIFODepths": [
      2
    ],
    "slr": -1
  },
  "ConvolutionInputGenerator_rtl_3": {
    "SIMD": 8,
    "parallel_window": 0,
    "ram_style": "distributed",
    "inFIFODepths": [
      2
    ],
    "outFIFODepths": [
      2
    ],
    "slr": -1
  },
  "MVAU_hls_8": {
    "PE": 1,
    "SIMD": 576,
    "ram_style": "auto",
    "resType": "dsp",
    "mem_mode": "internal_decoupled",
    "runtime_writeable_weights": 0,
    "inFIFODepths": [
      2
    ],
    "outFIFODepths": [
      2
    ],
    "slr": -1
  },
  "Thresholding_rtl_14": {
    "PE": 1,
    "runtime_writeable_weights": 0,
    "depth_trigger_uram": 0,
    "depth_trigger_bram": 0,
    "inFIFODepths": [
      2
    ],
    "outFIFODepths": [
      2
    ],
    "slr": -1
  },
  "MVAU_hls_9": {
    "PE": 4,
    "SIMD": 64,
    "ram_style": "auto",
    "resType": "auto",
    "mem_mode": "internal_decoupled",
    "runtime_writeable_weights": 0,
    "inFIFODepths": [
      2
    ],
    "outFIFODepths": [
      2
    ],
    "slr": -1
  },
  "Thresholding_rtl_15": {
    "PE": 4,
    "runtime_writeable_weights": 0,
    "depth_trigger_uram": 0,
    "depth_trigger_bram": 0,
    "inFIFODepths": [
      2
    ],
    "outFIFODepths": [
      2
    ],
    "slr": -1
  },
  "AddStreams_hls_2": {
    "PE": 4,
    "inFIFODepths": [
      2,
      2
    ],
    "outFIFODepths": [
      2
    ],
    "slr": -1
  },
  "Thresholding_rtl_16": {
    "PE": 4,
    "runtime_writeable_weights": 0,
    "depth_trigger_uram": 0,
    "depth_trigger_bram": 0,
    "inFIFODepths": [
      2
    ],
    "outFIFODepths": [
      2
    ],
    "slr": -1
  },
  "DuplicateStreams_hls_3": {
    "PE": 4,
    "inFIFODepths": [
      2
    ],
    "outFIFODepths": [
      2,
      2
    ],
    "slr": -1
  },
  "MVAU_hls_10": {
    "PE": 2,
    "SIMD": 256,
    "ram_style": "auto",
    "resType": "dsp",
    "mem_mode": "internal_decoupled",
    "runtime_writeable_weights": 0,
    "inFIFODepths": [
      2
    ],
    "outFIFODepths": [
      2
    ],
    "slr": -1
  },
  "DownSampler_hls_0": {
    "SIMD": 4,
    "inFIFODepths": [
      2
    ],
    "outFIFODepths": [
      2
    ],
    "slr": -1
  },
  "Thresholding_rtl_17": {
    "PE": 2,
    "runtime_writeable_weights": 0,
    "depth_trigger_uram": 0,
    "depth_trigger_bram": 0,
    "inFIFODepths": [
      2
    ],
    "outFIFODepths": [
      2
    ],
    "slr": -1
  },
  "MVAU_hls_11": {
    "PE": 2,
    "SIMD": 256,
    "ram_style": "auto",
    "resType": "dsp",
    "mem_mode": "internal_decoupled",
    "runtime_writeable_weights": 0,
    "inFIFODepths": [
      2
    ],
    "outFIFODepths": [
      2
    ],
    "slr": -1
  },
  "FMPadding_rtl_4": {
    "SIMD": 2,
    "inFIFODepths": [
      2
    ],
    "outFIFODepths": [
      2
    ],
    "slr": -1
  },
  "Thresholding_rtl_18": {
    "PE": 2,
    "runtime_writeable_weights": 0,
    "depth_trigger_uram": 0,
    "depth_trigger_bram": 0,
    "inFIFODepths": [
      2
    ],
    "outFIFODepths": [
      2
    ],
    "slr": -1
  },
  "ConvolutionInputGenerator_rtl_4": {
    "SIMD": 4,
    "parallel_window": 0,
    "ram_style": "distributed",
    "inFIFODepths": [
      2
    ],
    "outFIFODepths": [
      2
    ],
    "slr": -1
  },
  "MVAU_hls_12": {
    "PE": 1,
    "SIMD": 384,
    "ram_style": "auto",
    "resType": "dsp",
    "mem_mode": "internal_decoupled",
    "runtime_writeable_weights": 0,
    "inFIFODepths": [
      2
    ],
    "outFIFODepths": [
      2
    ],
    "slr": -1
  },
  "Thresholding_rtl_19": {
    "PE": 1,
    "runtime_writeable_weights": 0,
    "depth_trigger_uram": 0,
    "depth_trigger_bram": 0,
    "inFIFODepths": [
      2
    ],
    "outFIFODepths": [
      2
    ],
    "slr": -1
  },
  "MVAU_hls_13": {
    "PE": 2,
    "SIMD": 128,
    "ram_style": "auto",
    "resType": "dsp",
    "mem_mode": "internal_decoupled",
    "runtime_writeable_weights": 0,
    "inFIFODepths": [
      2
    ],
    "outFIFODepths": [
      2
    ],
    "slr": -1
  },
  "Thresholding_rtl_20": {
    "PE": 2,
    "runtime_writeable_weights": 0,
    "depth_trigger_uram": 0,
    "depth_trigger_bram": 0,
    "inFIFODepths": [
      2
    ],
    "outFIFODepths": [
      2
    ],
    "slr": -1
  },
  "AddStreams_hls_3": {
    "PE": 2,
    "inFIFODepths": [
      2,
      2
    ],
    "outFIFODepths": [
      2
    ],
    "slr": -1
  },
  "Thresholding_rtl_21": {
    "PE": 2,
    "runtime_writeable_weights": 0,
    "depth_trigger_uram": 0,
    "depth_trigger_bram": 0,
    "inFIFODepths": [
      2
    ],
    "outFIFODepths": [
      2
    ],
    "slr": -1
  },
  "DuplicateStreams_hls_4": {
    "PE": 2,
    "inFIFODepths": [
      2
    ],
    "outFIFODepths": [
      2,
      2
    ],
    "slr": -1
  },
  "MVAU_hls_14": {
    "PE": 1,
    "SIMD": 256,
    "ram_style": "auto",
    "resType": "auto",
    "mem_mode": "internal_decoupled",
    "runtime_writeable_weights": 0,
    "inFIFODepths": [
      2
    ],
    "outFIFODepths": [
      2
    ],
    "slr": -1
  },
  "Thresholding_rtl_22": {
    "PE": 2,
    "runtime_writeable_weights": 0,
    "depth_trigger_uram": 0,
    "depth_trigger_bram": 0,
    "inFIFODepths": [
      2
    ],
    "outFIFODepths": [
      2
    ],
    "slr": -1
  },
  "Thresholding_rtl_23": {
    "PE": 1,
    "runtime_writeable_weights": 0,
    "depth_trigger_uram": 0,
    "depth_trigger_bram": 0,
    "inFIFODepths": [
      2
    ],
    "outFIFODepths": [
      2
    ],
    "slr": -1
  },
  "FMPadding_rtl_5": {
    "SIMD": 1,
    "inFIFODepths": [
      2
    ],
    "outFIFODepths": [
      2
    ],
    "slr": -1
  },
  "ConvolutionInputGenerator_rtl_5": {
    "SIMD": 4,
    "parallel_window": 0,
    "ram_style": "distributed",
    "inFIFODepths": [
      2
    ],
    "outFIFODepths": [
      2
    ],
    "slr": -1
  },
  "MVAU_hls_15": {
    "PE": 1,
    "SIMD": 384,
    "ram_style": "auto",
    "resType": "dsp",
    "mem_mode": "internal_decoupled",
    "runtime_writeable_weights": 0,
    "inFIFODepths": [
      2
    ],
    "outFIFODepths": [
      2
    ],
    "slr": -1
  },
  "Thresholding_rtl_24": {
    "PE": 1,
    "runtime_writeable_weights": 0,
    "depth_trigger_uram": 0,
    "depth_trigger_bram": 0,
    "inFIFODepths": [
      2
    ],
    "outFIFODepths": [
      2
    ],
    "slr": -1
  },
  "MVAU_hls_16": {
    "PE": 2,
    "SIMD": 128,
    "ram_style": "auto",
    "resType": "dsp",
    "mem_mode": "internal_decoupled",
    "runtime_writeable_weights": 0,
    "inFIFODepths": [
      2
    ],
    "outFIFODepths": [
      2
    ],
    "slr": -1
  },
  "Thresholding_rtl_25": {
    "PE": 2,
    "runtime_writeable_weights": 0,
    "depth_trigger_uram": 0,
    "depth_trigger_bram": 0,
    "inFIFODepths": [
      2
    ],
    "outFIFODepths": [
      2
    ],
    "slr": -1
  },
  "AddStreams_hls_4": {
    "PE": 2,
    "inFIFODepths": [
      2,
      2
    ],
    "outFIFODepths": [
      2
    ],
    "slr": -1
  },
  "Thresholding_rtl_26": {
    "PE": 2,
    "runtime_writeable_weights": 0,
    "depth_trigger_uram": 0,
    "depth_trigger_bram": 0,
    "inFIFODepths": [
      2
    ],
    "outFIFODepths": [
      2
    ],
    "slr": -1
  },
  "DuplicateStreams_hls_5": {
    "PE": 2,
    "inFIFODepths": [
      2
    ],
    "outFIFODepths": [
      2,
      2
    ],
    "slr": -1
  },
  "MVAU_hls_17": {
    "PE": 1,
    "SIMD": 256,
    "ram_style": "auto",
    "resType": "auto",
    "mem_mode": "internal_decoupled",
    "runtime_writeable_weights": 0,
    "inFIFODepths": [
      2
    ],
    "outFIFODepths": [
      2
    ],
    "slr": -1
  },
  "Thresholding_rtl_27": {
    "PE": 2,
    "runtime_writeable_weights": 0,
    "depth_trigger_uram": 0,
    "depth_trigger_bram": 0,
    "inFIFODepths": [
      2
    ],
    "outFIFODepths": [
      2
    ],
    "slr": -1
  },
  "Thresholding_rtl_28": {
    "PE": 1,
    "runtime_writeable_weights": 0,
    "depth_trigger_uram": 0,
    "depth_trigger_bram": 0,
    "inFIFODepths": [
      2
    ],
    "outFIFODepths": [
      2
    ],
    "slr": -1
  },
  "FMPadding_rtl_6": {
    "SIMD": 1,
    "inFIFODepths": [
      2
    ],
    "outFIFODepths": [
      2
    ],
    "slr": -1
  },
  "ConvolutionInputGenerator_rtl_6": {
    "SIMD": 4,
    "parallel_window": 0,
    "ram_style": "distributed",
    "inFIFODepths": [
      2
    ],
    "outFIFODepths": [
      2
    ],
    "slr": -1
  },
  "MVAU_hls_18": {
    "PE": 1,
    "SIMD": 384,
    "ram_style": "auto",
    "resType": "dsp",
    "mem_mode": "internal_decoupled",
    "runtime_writeable_weights": 0,
    "inFIFODepths": [
      2
    ],
    "outFIFODepths": [
      2
    ],
    "slr": -1
  },
  "Thresholding_rtl_29": {
    "PE": 1,
    "runtime_writeable_weights": 0,
    "depth_trigger_uram": 0,
    "depth_trigger_bram": 0,
    "inFIFODepths": [
      2
    ],
    "outFIFODepths": [
      2
    ],
    "slr": -1
  },
  "MVAU_hls_19": {
    "PE": 1,
    "SIMD": 128,
    "ram_style": "auto",
    "resType": "auto",
    "mem_mode": "internal_decoupled",
    "runtime_writeable_weights": 0,
    "inFIFODepths": [
      2
    ],
    "outFIFODepths": [
      2
    ],
    "slr": -1
  },
  "Thresholding_rtl_30": {
    "PE": 1,
    "runtime_writeable_weights": 0,
    "depth_trigger_uram": 0,
    "depth_trigger_bram": 0,
    "inFIFODepths": [
      2
    ],
    "outFIFODepths": [
      2
    ],
    "slr": -1
  },
  "AddStreams_hls_5": {
    "PE": 1,
    "inFIFODepths": [
      2,
      2
    ],
    "outFIFODepths": [
      2
    ],
    "slr": -1
  },
  "Thresholding_rtl_31": {
    "PE": 1,
    "runtime_writeable_weights": 0,
    "depth_trigger_uram": 0,
    "depth_trigger_bram": 0,
    "inFIFODepths": [
      2
    ],
    "outFIFODepths": [
      2
    ],
    "slr": -1
  },
  "DuplicateStreams_hls_6": {
    "PE": 1,
    "inFIFODepths": [
      2
    ],
    "outFIFODepths": [
      2,
      2
    ],
    "slr": -1
  },
  "MVAU_hls_20": {
    "PE": 1,
    "SIMD": 128,
    "ram_style": "auto",
    "resType": "auto",
    "mem_mode": "internal_decoupled",
    "runtime_writeable_weights": 0,
    "inFIFODepths": [
      2
    ],
    "outFIFODepths": [
      2
    ],
    "slr": -1
  },
  "Thresholding_rtl_32": {
    "PE": 1,
    "runtime_writeable_weights": 0,
    "depth_trigger_uram": 0,
    "depth_trigger_bram": 0,
    "inFIFODepths": [
      2
    ],
    "outFIFODepths": [
      2
    ],
    "slr": -1
  },
  "Thresholding_rtl_33": {
    "PE": 1,
    "runtime_writeable_weights": 0,
    "depth_trigger_uram": 0,
    "depth_trigger_bram": 0,
    "inFIFODepths": [
      2
    ],
    "outFIFODepths": [
      2
    ],
    "slr": -1
  },
  "FMPadding_rtl_7": {
    "SIMD": 1,
    "inFIFODepths": [
      2
    ],
    "outFIFODepths": [
      2
    ],
    "slr": -1
  },
  "ConvolutionInputGenerator_rtl_7": {
    "SIMD": 4,
    "parallel_window": 0,
    "ram_style": "distributed",
    "inFIFODepths": [
      2
    ],
    "outFIFODepths": [
      2
    ],
    "slr": -1
  },
  "MVAU_hls_21": {
    "PE": 1,
    "SIMD": 288,
    "ram_style": "auto",
    "resType": "dsp",
    "mem_mode": "internal_decoupled",
    "runtime_writeable_weights": 0,
    "inFIFODepths": [
      2
    ],
    "outFIFODepths": [
      2
    ],
    "slr": -1
  },
  "Thresholding_rtl_34": {
    "PE": 1,
    "runtime_writeable_weights": 0,
    "depth_trigger_uram": 0,
    "depth_trigger_bram": 0,
    "inFIFODepths": [
      2
    ],
    "outFIFODepths": [
      2
    ],
    "slr": -1
  },
  "MVAU_hls_22": {
    "PE": 1,
    "SIMD": 128,
    "ram_style": "auto",
    "resType": "auto",
    "mem_mode": "internal_decoupled",
    "runtime_writeable_weights": 0,
    "inFIFODepths": [
      2
    ],
    "outFIFODepths": [
      2
    ],
    "slr": -1
  },
  "Thresholding_rtl_35": {
    "PE": 1,
    "runtime_writeable_weights": 0,
    "depth_trigger_uram": 0,
    "depth_trigger_bram": 0,
    "inFIFODepths": [
      2
    ],
    "outFIFODepths": [
      2
    ],
    "slr": -1
  },
  "AddStreams_hls_6": {
    "PE": 1,
    "inFIFODepths": [
      2,
      2
    ],
    "outFIFODepths": [
      2
    ],
    "slr": -1
  },
  "Thresholding_rtl_36": {
    "PE": 1,
    "runtime_writeable_weights": 0,
    "depth_trigger_uram": 0,
    "depth_trigger_bram": 0,
    "inFIFODepths": [
      2
    ],
    "outFIFODepths": [
      2
    ],
    "slr": -1
  },
  "DuplicateStreams_hls_7": {
    "PE": 1,
    "inFIFODepths": [
      2
    ],
    "outFIFODepths": [
      2,
      2
    ],
    "slr": -1
  },
  "MVAU_hls_23": {
    "PE": 1,
    "SIMD": 256,
    "ram_style": "auto",
    "resType": "auto",
    "mem_mode": "internal_decoupled",
    "runtime_writeable_weights": 0,
    "inFIFODepths": [
      2
    ],
    "outFIFODepths": [
      2
    ],
    "slr": -1
  },
  "DownSampler_hls_1": {
    "SIMD": 1,
    "inFIFODepths": [
      2
    ],
    "outFIFODepths": [
      2
    ],
    "slr": -1
  },
  "Thresholding_rtl_37": {
    "PE": 1,
    "runtime_writeable_weights": 0,
    "depth_trigger_uram": 0,
    "depth_trigger_bram": 0,
    "inFIFODepths": [
      2
    ],
    "outFIFODepths": [
      2
    ],
    "slr": -1
  },
  "MVAU_hls_24": {
    "PE": 1,
    "SIMD": 256,
    "ram_style": "auto",
    "resType": "auto",
    "mem_mode": "internal_decoupled",
    "runtime_writeable_weights": 0,
    "inFIFODepths": [
      2
    ],
    "outFIFODepths": [
      2
    ],
    "slr": -1
  },
  "FMPadding_rtl_8": {
    "SIMD": 1,
    "inFIFODepths": [
      2
    ],
    "outFIFODepths": [
      2
    ],
    "slr": -1
  },
  "Thresholding_rtl_38": {
    "PE": 1,
    "runtime_writeable_weights": 0,
    "depth_trigger_uram": 0,
    "depth_trigger_bram": 0,
    "inFIFODepths": [
      2
    ],
    "outFIFODepths": [
      2
    ],
    "slr": -1
  },
  "ConvolutionInputGenerator_rtl_8": {
    "SIMD": 2,
    "parallel_window": 0,
    "ram_style": "distributed",
    "inFIFODepths": [
      2
    ],
    "outFIFODepths": [
      2
    ],
    "slr": -1
  },
  "MVAU_hls_25": {
    "PE": 1,
    "SIMD": 288,
    "ram_style": "auto",
    "resType": "dsp",
    "mem_mode": "internal_decoupled",
    "runtime_writeable_weights": 0,
    "inFIFODepths": [
      2
    ],
    "outFIFODepths": [
      2
    ],
    "slr": -1
  },
  "Thresholding_rtl_39": {
    "PE": 1,
    "runtime_writeable_weights": 0,
    "depth_trigger_uram": 0,
    "depth_trigger_bram": 0,
    "inFIFODepths": [
      2
    ],
    "outFIFODepths": [
      2
    ],
    "slr": -1
  },
  "MVAU_hls_26": {
    "PE": 1,
    "SIMD": 128,
    "ram_style": "auto",
    "resType": "auto",
    "mem_mode": "internal_decoupled",
    "runtime_writeable_weights": 0,
    "inFIFODepths": [
      2
    ],
    "outFIFODepths": [
      2
    ],
    "slr": -1
  },
  "Thresholding_rtl_40": {
    "PE": 1,
    "runtime_writeable_weights": 0,
    "depth_trigger_uram": 0,
    "depth_trigger_bram": 0,
    "inFIFODepths": [
      2
    ],
    "outFIFODepths": [
      2
    ],
    "slr": -1
  },
  "AddStreams_hls_7": {
    "PE": 1,
    "inFIFODepths": [
      2,
      2
    ],
    "outFIFODepths": [
      2
    ],
    "slr": -1
  },
  "Thresholding_rtl_41": {
    "PE": 1,
    "runtime_writeable_weights": 0,
    "depth_trigger_uram": 0,
    "depth_trigger_bram": 0,
    "inFIFODepths": [
      2
    ],
    "outFIFODepths": [
      2
    ],
    "slr": -1
  },
  "DuplicateStreams_hls_8": {
    "PE": 1,
    "inFIFODepths": [
      2
    ],
    "outFIFODepths": [
      2,
      2
    ],
    "slr": -1
  },
  "MVAU_hls_27": {
    "PE": 1,
    "SIMD": 128,
    "ram_style": "auto",
    "resType": "auto",
    "mem_mode": "internal_decoupled",
    "runtime_writeable_weights": 0,
    "inFIFODepths": [
      2
    ],
    "outFIFODepths": [
      2
    ],
    "slr": -1
  },
  "Thresholding_rtl_42": {
    "PE": 1,
    "runtime_writeable_weights": 0,
    "depth_trigger_uram": 0,
    "depth_trigger_bram": 0,
    "inFIFODepths": [
      2
    ],
    "outFIFODepths": [
      2
    ],
    "slr": -1
  },
  "Thresholding_rtl_43": {
    "PE": 1,
    "runtime_writeable_weights": 0,
    "depth_trigger_uram": 0,
    "depth_trigger_bram": 0,
    "inFIFODepths": [
      2
    ],
    "outFIFODepths": [
      2
    ],
    "slr": -1
  },
  "FMPadding_rtl_9": {
    "SIMD": 1,
    "inFIFODepths": [
      2
    ],
    "outFIFODepths": [
      2
    ],
    "slr": -1
  },
  "ConvolutionInputGenerator_rtl_9": {
    "SIMD": 2,
    "parallel_window": 0,
    "ram_style": "distributed",
    "inFIFODepths": [
      2
    ],
    "outFIFODepths": [
      2
    ],
    "slr": -1
  },
  "MVAU_hls_28": {
    "PE": 1,
    "SIMD": 288,
    "ram_style": "auto",
    "resType": "auto",
    "mem_mode": "internal_decoupled",
    "runtime_writeable_weights": 0,
    "inFIFODepths": [
      2
    ],
    "outFIFODepths": [
      2
    ],
    "slr": -1
  },
  "Thresholding_rtl_44": {
    "PE": 1,
    "runtime_writeable_weights": 0,
    "depth_trigger_uram": 0,
    "depth_trigger_bram": 0,
    "inFIFODepths": [
      2
    ],
    "outFIFODepths": [
      2
    ],
    "slr": -1
  },
  "MVAU_hls_29": {
    "PE": 1,
    "SIMD": 128,
    "ram_style": "auto",
    "resType": "auto",
    "mem_mode": "internal_decoupled",
    "runtime_writeable_weights": 0,
    "inFIFODepths": [
      2
    ],
    "outFIFODepths": [
      2
    ],
    "slr": -1
  },
  "Thresholding_rtl_45": {
    "PE": 1,
    "runtime_writeable_weights": 0,
    "depth_trigger_uram": 0,
    "depth_trigger_bram": 0,
    "inFIFODepths": [
      2
    ],
    "outFIFODepths": [
      2
    ],
    "slr": -1
  },
  "AddStreams_hls_8": {
    "PE": 1,
    "inFIFODepths": [
      2,
      2
    ],
    "outFIFODepths": [
      2
    ],
    "slr": -1
  },
  "Thresholding_rtl_46": {
    "PE": 1,
    "runtime_writeable_weights": 0,
    "depth_trigger_uram": 0,
    "depth_trigger_bram": 0,
    "inFIFODepths": [
      2
    ],
    "outFIFODepths": [
      2
    ],
    "slr": -1
  },
  "DuplicateStreams_hls_9": {
    "PE": 1,
    "inFIFODepths": [
      2
    ],
    "outFIFODepths": [
      2,
      2
    ],
    "slr": -1
  },
  "MVAU_hls_30": {
    "PE": 1,
    "SIMD": 128,
    "ram_style": "auto",
    "resType": "auto",
    "mem_mode": "internal_decoupled",
    "runtime_writeable_weights": 0,
    "inFIFODepths": [
      2
    ],
    "outFIFODepths": [
      2
    ],
    "slr": -1
  },
  "Thresholding_rtl_47": {
    "PE": 1,
    "runtime_writeable_weights": 0,
    "depth_trigger_uram": 0,
    "depth_trigger_bram": 0,
    "inFIFODepths": [
      2
    ],
    "outFIFODepths": [
      2
    ],
    "slr": -1
  },
  "Thresholding_rtl_48": {
    "PE": 1,
    "runtime_writeable_weights": 0,
    "depth_trigger_uram": 0,
    "depth_trigger_bram": 0,
    "inFIFODepths": [
      2
    ],
    "outFIFODepths": [
      2
    ],
    "slr": -1
  },
  "FMPadding_rtl_10": {
    "SIMD": 1,
    "inFIFODepths": [
      2
    ],
    "outFIFODepths": [
      2
    ],
    "slr": -1
  },
  "ConvolutionInputGenerator_rtl_10": {
    "SIMD": 2,
    "parallel_window": 0,
    "ram_style": "distributed",
    "inFIFODepths": [
      2
    ],
    "outFIFODepths": [
      2
    ],
    "slr": -1
  },
  "MVAU_hls_31": {
    "PE": 1,
    "SIMD": 288,
    "ram_style": "auto",
    "resType": "auto",
    "mem_mode": "internal_decoupled",
    "runtime_writeable_weights": 0,
    "inFIFODepths": [
      2
    ],
    "outFIFODepths": [
      2
    ],
    "slr": -1
  },
  "Thresholding_rtl_49": {
    "PE": 1,
    "runtime_writeable_weights": 0,
    "depth_trigger_uram": 0,
    "depth_trigger_bram": 0,
    "inFIFODepths": [
      2
    ],
    "outFIFODepths": [
      2
    ],
    "slr": -1
  },
  "MVAU_hls_32": {
    "PE": 1,
    "SIMD": 128,
    "ram_style": "auto",
    "resType": "auto",
    "mem_mode": "internal_decoupled",
    "runtime_writeable_weights": 0,
    "inFIFODepths": [
      2
    ],
    "outFIFODepths": [
      2
    ],
    "slr": -1
  },
  "Thresholding_rtl_50": {
    "PE": 1,
    "runtime_writeable_weights": 0,
    "depth_trigger_uram": 0,
    "depth_trigger_bram": 0,
    "inFIFODepths": [
      2
    ],
    "outFIFODepths": [
      2
    ],
    "slr": -1
  },
  "AddStreams_hls_9": {
    "PE": 1,
    "inFIFODepths": [
      2,
      2
    ],
    "outFIFODepths": [
      2
    ],
    "slr": -1
  },
  "Thresholding_rtl_51": {
    "PE": 1,
    "runtime_writeable_weights": 0,
    "depth_trigger_uram": 0,
    "depth_trigger_bram": 0,
    "inFIFODepths": [
      2
    ],
    "outFIFODepths": [
      2
    ],
    "slr": -1
  },
  "DuplicateStreams_hls_10": {
    "PE": 1,
    "inFIFODepths": [
      2
    ],
    "outFIFODepths": [
      2,
      2
    ],
    "slr": -1
  },
  "MVAU_hls_33": {
    "PE": 1,
    "SIMD": 128,
    "ram_style": "auto",
    "resType": "auto",
    "mem_mode": "internal_decoupled",
    "runtime_writeable_weights": 0,
    "inFIFODepths": [
      2
    ],
    "outFIFODepths": [
      2
    ],
    "slr": -1
  },
  "Thresholding_rtl_52": {
    "PE": 1,
    "runtime_writeable_weights": 0,
    "depth_trigger_uram": 0,
    "depth_trigger_bram": 0,
    "inFIFODepths": [
      2
    ],
    "outFIFODepths": [
      2
    ],
    "slr": -1
  },
  "Thresholding_rtl_53": {
    "PE": 1,
    "runtime_writeable_weights": 0,
    "depth_trigger_uram": 0,
    "depth_trigger_bram": 0,
    "inFIFODepths": [
      2
    ],
    "outFIFODepths": [
      2
    ],
    "slr": -1
  },
  "FMPadding_rtl_11": {
    "SIMD": 1,
    "inFIFODepths": [
      2
    ],
    "outFIFODepths": [
      2
    ],
    "slr": -1
  },
  "ConvolutionInputGenerator_rtl_11": {
    "SIMD": 2,
    "parallel_window": 0,
    "ram_style": "distributed",
    "inFIFODepths": [
      2
    ],
    "outFIFODepths": [
      2
    ],
    "slr": -1
  },
  "MVAU_hls_34": {
    "PE": 1,
    "SIMD": 288,
    "ram_style": "auto",
    "resType": "dsp",
    "mem_mode": "internal_decoupled",
    "runtime_writeable_weights": 0,
    "inFIFODepths": [
      2
    ],
    "outFIFODepths": [
      2
    ],
    "slr": -1
  },
  "Thresholding_rtl_54": {
    "PE": 1,
    "runtime_writeable_weights": 0,
    "depth_trigger_uram": 0,
    "depth_trigger_bram": 0,
    "inFIFODepths": [
      2
    ],
    "outFIFODepths": [
      2
    ],
    "slr": -1
  },
  "MVAU_hls_35": {
    "PE": 1,
    "SIMD": 128,
    "ram_style": "auto",
    "resType": "auto",
    "mem_mode": "internal_decoupled",
    "runtime_writeable_weights": 0,
    "inFIFODepths": [
      2
    ],
    "outFIFODepths": [
      2
    ],
    "slr": -1
  },
  "Thresholding_rtl_55": {
    "PE": 1,
    "runtime_writeable_weights": 0,
    "depth_trigger_uram": 0,
    "depth_trigger_bram": 0,
    "inFIFODepths": [
      2
    ],
    "outFIFODepths": [
      2
    ],
    "slr": -1
  },
  "AddStreams_hls_10": {
    "PE": 1,
    "inFIFODepths": [
      2,
      2
    ],
    "outFIFODepths": [
      2
    ],
    "slr": -1
  },
  "Thresholding_rtl_56": {
    "PE": 1,
    "runtime_writeable_weights": 0,
    "depth_trigger_uram": 0,
    "depth_trigger_bram": 0,
    "inFIFODepths": [
      2
    ],
    "outFIFODepths": [
      2
    ],
    "slr": -1
  },
  "DuplicateStreams_hls_11": {
    "PE": 1,
    "inFIFODepths": [
      2
    ],
    "outFIFODepths": [
      2,
      2
    ],
    "slr": -1
  },
  "MVAU_hls_36": {
    "PE": 1,
    "SIMD": 128,
    "ram_style": "auto",
    "resType": "auto",
    "mem_mode": "internal_decoupled",
    "runtime_writeable_weights": 0,
    "inFIFODepths": [
      2
    ],
    "outFIFODepths": [
      2
    ],
    "slr": -1
  },
  "Thresholding_rtl_57": {
    "PE": 1,
    "runtime_writeable_weights": 0,
    "depth_trigger_uram": 0,
    "depth_trigger_bram": 0,
    "inFIFODepths": [
      2
    ],
    "outFIFODepths": [
      2
    ],
    "slr": -1
  },
  "Thresholding_rtl_58": {
    "PE": 1,
    "runtime_writeable_weights": 0,
    "depth_trigger_uram": 0,
    "depth_trigger_bram": 0,
    "inFIFODepths": [
      2
    ],
    "outFIFODepths": [
      2
    ],
    "slr": -1
  },
  "FMPadding_rtl_12": {
    "SIMD": 1,
    "inFIFODepths": [
      2
    ],
    "outFIFODepths": [
      2
    ],
    "slr": -1
  },
  "ConvolutionInputGenerator_rtl_12": {
    "SIMD": 2,
    "parallel_window": 0,
    "ram_style": "distributed",
    "inFIFODepths": [
      2
    ],
    "outFIFODepths": [
      2
    ],
    "slr": -1
  },
  "MVAU_hls_37": {
    "PE": 1,
    "SIMD": 288,
    "ram_style": "auto",
    "resType": "auto",
    "mem_mode": "internal_decoupled",
    "runtime_writeable_weights": 0,
    "inFIFODepths": [
      2
    ],
    "outFIFODepths": [
      2
    ],
    "slr": -1
  },
  "Thresholding_rtl_59": {
    "PE": 1,
    "runtime_writeable_weights": 0,
    "depth_trigger_uram": 0,
    "depth_trigger_bram": 0,
    "inFIFODepths": [
      2
    ],
    "outFIFODepths": [
      2
    ],
    "slr": -1
  },
  "MVAU_hls_38": {
    "PE": 1,
    "SIMD": 128,
    "ram_style": "auto",
    "resType": "auto",
    "mem_mode": "internal_decoupled",
    "runtime_writeable_weights": 0,
    "inFIFODepths": [
      2
    ],
    "outFIFODepths": [
      2
    ],
    "slr": -1
  },
  "Thresholding_rtl_60": {
    "PE": 1,
    "runtime_writeable_weights": 0,
    "depth_trigger_uram": 0,
    "depth_trigger_bram": 0,
    "inFIFODepths": [
      2
    ],
    "outFIFODepths": [
      2
    ],
    "slr": -1
  },
  "AddStreams_hls_11": {
    "PE": 1,
    "inFIFODepths": [
      2,
      2
    ],
    "outFIFODepths": [
      2
    ],
    "slr": -1
  },
  "Thresholding_rtl_61": {
    "PE": 1,
    "runtime_writeable_weights": 0,
    "depth_trigger_uram": 0,
    "depth_trigger_bram": 0,
    "inFIFODepths": [
      2
    ],
    "outFIFODepths": [
      2
    ],
    "slr": -1
  },
  "DuplicateStreams_hls_12": {
    "PE": 1,
    "inFIFODepths": [
      2
    ],
    "outFIFODepths": [
      2,
      2
    ],
    "slr": -1
  },
  "MVAU_hls_39": {
    "PE": 1,
    "SIMD": 128,
    "ram_style": "auto",
    "resType": "auto",
    "mem_mode": "internal_decoupled",
    "runtime_writeable_weights": 0,
    "inFIFODepths": [
      2
    ],
    "outFIFODepths": [
      2
    ],
    "slr": -1
  },
  "Thresholding_rtl_62": {
    "PE": 1,
    "runtime_writeable_weights": 0,
    "depth_trigger_uram": 0,
    "depth_trigger_bram": 0,
    "inFIFODepths": [
      2
    ],
    "outFIFODepths": [
      2
    ],
    "slr": -1
  },
  "Thresholding_rtl_63": {
    "PE": 1,
    "runtime_writeable_weights": 0,
    "depth_trigger_uram": 0,
    "depth_trigger_bram": 0,
    "inFIFODepths": [
      2
    ],
    "outFIFODepths": [
      2
    ],
    "slr": -1
  },
  "FMPadding_rtl_13": {
    "SIMD": 1,
    "inFIFODepths": [
      2
    ],
    "outFIFODepths": [
      2
    ],
    "slr": -1
  },
  "ConvolutionInputGenerator_rtl_13": {
    "SIMD": 2,
    "parallel_window": 0,
    "ram_style": "distributed",
    "inFIFODepths": [
      2
    ],
    "outFIFODepths": [
      2
    ],
    "slr": -1
  },
  "MVAU_hls_40": {
    "PE": 1,
    "SIMD": 288,
    "ram_style": "auto",
    "resType": "dsp",
    "mem_mode": "internal_decoupled",
    "runtime_writeable_weights": 0,
    "inFIFODepths": [
      2
    ],
    "outFIFODepths": [
      2
    ],
    "slr": -1
  },
  "Thresholding_rtl_64": {
    "PE": 1,
    "runtime_writeable_weights": 0,
    "depth_trigger_uram": 0,
    "depth_trigger_bram": 0,
    "inFIFODepths": [
      2
    ],
    "outFIFODepths": [
      2
    ],
    "slr": -1
  },
  "MVAU_hls_41": {
    "PE": 1,
    "SIMD": 128,
    "ram_style": "auto",
    "resType": "auto",
    "mem_mode": "internal_decoupled",
    "runtime_writeable_weights": 0,
    "inFIFODepths": [
      2
    ],
    "outFIFODepths": [
      2
    ],
    "slr": -1
  },
  "Thresholding_rtl_65": {
    "PE": 1,
    "runtime_writeable_weights": 0,
    "depth_trigger_uram": 0,
    "depth_trigger_bram": 0,
    "inFIFODepths": [
      2
    ],
    "outFIFODepths": [
      2
    ],
    "slr": -1
  },
  "AddStreams_hls_12": {
    "PE": 1,
    "inFIFODepths": [
      2,
      2
    ],
    "outFIFODepths": [
      2
    ],
    "slr": -1
  },
  "Thresholding_rtl_66": {
    "PE": 1,
    "runtime_writeable_weights": 0,
    "depth_trigger_uram": 0,
    "depth_trigger_bram": 0,
    "inFIFODepths": [
      2
    ],
    "outFIFODepths": [
      2
    ],
    "slr": -1
  },
  "DuplicateStreams_hls_13": {
    "PE": 1,
    "inFIFODepths": [
      2
    ],
    "outFIFODepths": [
      2,
      2
    ],
    "slr": -1
  },
  "MVAU_hls_42": {
    "PE": 1,
    "SIMD": 256,
    "ram_style": "auto",
    "resType": "dsp",
    "mem_mode": "internal_decoupled",
    "runtime_writeable_weights": 0,
    "inFIFODepths": [
      2
    ],
    "outFIFODepths": [
      2
    ],
    "slr": -1
  },
  "DownSampler_hls_2": {
    "SIMD": 1,
    "inFIFODepths": [
      2
    ],
    "outFIFODepths": [
      2
    ],
    "slr": -1
  },
  "Thresholding_rtl_67": {
    "PE": 1,
    "runtime_writeable_weights": 0,
    "depth_trigger_uram": 0,
    "depth_trigger_bram": 0,
    "inFIFODepths": [
      2
    ],
    "outFIFODepths": [
      2
    ],
    "slr": -1
  },
  "MVAU_hls_43": {
    "PE": 1,
    "SIMD": 256,
    "ram_style": "distributed",
    "resType": "dsp",
    "mem_mode": "internal_decoupled",
    "runtime_writeable_weights": 0,
    "inFIFODepths": [
      2
    ],
    "outFIFODepths": [
      2
    ],
    "slr": -1
  },
  "FMPadding_rtl_14": {
    "SIMD": 1,
    "inFIFODepths": [
      2
    ],
    "outFIFODepths": [
      2
    ],
    "slr": -1
  },
  "Thresholding_rtl_68": {
    "PE": 1,
    "runtime_writeable_weights": 0,
    "depth_trigger_uram": 0,
    "depth_trigger_bram": 0,
    "inFIFODepths": [
      2
    ],
    "outFIFODepths": [
      2
    ],
    "slr": -1
  },
  "ConvolutionInputGenerator_rtl_14": {
    "SIMD": 1,
    "parallel_window": 0,
    "ram_style": "distributed",
    "inFIFODepths": [
      2
    ],
    "outFIFODepths": [
      2
    ],
    "slr": -1
  },
  "MVAU_hls_44": {
    "PE": 1,
    "SIMD": 288,
    "ram_style": "distributed",
    "resType": "dsp",
    "mem_mode": "internal_decoupled",
    "runtime_writeable_weights": 0,
    "inFIFODepths": [
      2
    ],
    "outFIFODepths": [
      2
    ],
    "slr": -1
  },
  "Thresholding_rtl_69": {
    "PE": 1,
    "runtime_writeable_weights": 0,
    "depth_trigger_uram": 0,
    "depth_trigger_bram": 0,
    "inFIFODepths": [
      2
    ],
    "outFIFODepths": [
      2
    ],
    "slr": -1
  },
  "MVAU_hls_45": {
    "PE": 1,
    "SIMD": 128,
    "ram_style": "distributed",
    "resType": "dsp",
    "mem_mode": "internal_decoupled",
    "runtime_writeable_weights": 0,
    "inFIFODepths": [
      2
    ],
    "outFIFODepths": [
      2
    ],
    "slr": -1
  },
  "Thresholding_rtl_70": {
    "PE": 1,
    "runtime_writeable_weights": 0,
    "depth_trigger_uram": 0,
    "depth_trigger_bram": 0,
    "inFIFODepths": [
      2
    ],
    "outFIFODepths": [
      2
    ],
    "slr": -1
  },
  "AddStreams_hls_13": {
    "PE": 1,
    "inFIFODepths": [
      2,
      2
    ],
    "outFIFODepths": [
      2
    ],
    "slr": -1
  },
  "Thresholding_rtl_71": {
    "PE": 1,
    "runtime_writeable_weights": 0,
    "depth_trigger_uram": 0,
    "depth_trigger_bram": 0,
    "inFIFODepths": [
      2
    ],
    "outFIFODepths": [
      2
    ],
    "slr": -1
  },
  "DuplicateStreams_hls_14": {
    "PE": 1,
    "inFIFODepths": [
      2
    ],
    "outFIFODepths": [
      2,
      2
    ],
    "slr": -1
  },
  "MVAU_hls_46": {
    "PE": 1,
    "SIMD": 128,
    "ram_style": "distributed",
    "resType": "dsp",
    "mem_mode": "internal_decoupled",
    "runtime_writeable_weights": 0,
    "inFIFODepths": [
      2
    ],
    "outFIFODepths": [
      2
    ],
    "slr": -1
  },
  "Thresholding_rtl_72": {
    "PE": 1,
    "runtime_writeable_weights": 0,
    "depth_trigger_uram": 0,
    "depth_trigger_bram": 0,
    "inFIFODepths": [
      2
    ],
    "outFIFODepths": [
      2
    ],
    "slr": -1
  },
  "Thresholding_rtl_73": {
    "PE": 1,
    "runtime_writeable_weights": 0,
    "depth_trigger_uram": 0,
    "depth_trigger_bram": 0,
    "inFIFODepths": [
      2
    ],
    "outFIFODepths": [
      2
    ],
    "slr": -1
  },
  "FMPadding_rtl_15": {
    "SIMD": 1,
    "inFIFODepths": [
      2
    ],
    "outFIFODepths": [
      2
    ],
    "slr": -1
  },
  "ConvolutionInputGenerator_rtl_15": {
    "SIMD": 1,
    "parallel_window": 0,
    "ram_style": "distributed",
    "inFIFODepths": [
      2
    ],
    "outFIFODepths": [
      2
    ],
    "slr": -1
  },
  "MVAU_hls_47": {
    "PE": 1,
    "SIMD": 288,
    "ram_style": "distributed",
    "resType": "dsp",
    "mem_mode": "internal_decoupled",
    "runtime_writeable_weights": 0,
    "inFIFODepths": [
      2
    ],
    "outFIFODepths": [
      2
    ],
    "slr": -1
  },
  "Thresholding_rtl_74": {
    "PE": 1,
    "runtime_writeable_weights": 0,
    "depth_trigger_uram": 0,
    "depth_trigger_bram": 0,
    "inFIFODepths": [
      2
    ],
    "outFIFODepths": [
      2
    ],
    "slr": -1
  },
  "MVAU_hls_48": {
    "PE": 1,
    "SIMD": 128,
    "ram_style": "distributed",
    "resType": "dsp",
    "mem_mode": "internal_decoupled",
    "runtime_writeable_weights": 0,
    "inFIFODepths": [
      2
    ],
    "outFIFODepths": [
      2
    ],
    "slr": -1
  },
  "Thresholding_rtl_75": {
    "PE": 1,
    "runtime_writeable_weights": 0,
    "depth_trigger_uram": 0,
    "depth_trigger_bram": 0,
    "inFIFODepths": [
      2
    ],
    "outFIFODepths": [
      2
    ],
    "slr": -1
  },
  "AddStreams_hls_14": {
    "PE": 1,
    "inFIFODepths": [
      2,
      2
    ],
    "outFIFODepths": [
      2
    ],
    "slr": -1
  },
  "Thresholding_rtl_76": {
    "PE": 1,
    "runtime_writeable_weights": 0,
    "depth_trigger_uram": 0,
    "depth_trigger_bram": 0,
    "inFIFODepths": [
      2
    ],
    "outFIFODepths": [
      2
    ],
    "slr": -1
  },
  "DuplicateStreams_hls_15": {
    "PE": 1,
    "inFIFODepths": [
      2
    ],
    "outFIFODepths": [
      2,
      2
    ],
    "slr": -1
  },
  "MVAU_hls_49": {
    "PE": 1,
    "SIMD": 128,
    "ram_style": "distributed",
    "resType": "dsp",
    "mem_mode": "internal_decoupled",
    "runtime_writeable_weights": 0,
    "inFIFODepths": [
      2
    ],
    "outFIFODepths": [
      2
    ],
    "slr": -1
  },
  "Thresholding_rtl_77": {
    "PE": 1,
    "runtime_writeable_weights": 0,
    "depth_trigger_uram": 0,
    "depth_trigger_bram": 0,
    "inFIFODepths": [
      2
    ],
    "outFIFODepths": [
      2
    ],
    "slr": -1
  },
  "Thresholding_rtl_78": {
    "PE": 1,
    "runtime_writeable_weights": 0,
    "depth_trigger_uram": 0,
    "depth_trigger_bram": 0,
    "inFIFODepths": [
      2
    ],
    "outFIFODepths": [
      2
    ],
    "slr": -1
  },
  "FMPadding_rtl_16": {
    "SIMD": 1,
    "inFIFODepths": [
      2
    ],
    "outFIFODepths": [
      2
    ],
    "slr": -1
  },
  "ConvolutionInputGenerator_rtl_16": {
    "SIMD": 1,
    "parallel_window": 0,
    "ram_style": "distributed",
    "inFIFODepths": [
      2
    ],
    "outFIFODepths": [
      2
    ],
    "slr": -1
  },
  "MVAU_hls_50": {
    "PE": 1,
    "SIMD": 288,
    "ram_style": "distributed",
    "resType": "dsp",
    "mem_mode": "internal_decoupled",
    "runtime_writeable_weights": 0,
    "inFIFODepths": [
      2
    ],
    "outFIFODepths": [
      2
    ],
    "slr": -1
  },
  "Thresholding_rtl_79": {
    "PE": 1,
    "runtime_writeable_weights": 0,
    "depth_trigger_uram": 0,
    "depth_trigger_bram": 0,
    "inFIFODepths": [
      2
    ],
    "outFIFODepths": [
      2
    ],
    "slr": -1
  },
  "MVAU_hls_51": {
    "PE": 1,
    "SIMD": 128,
    "ram_style": "distributed",
    "resType": "dsp",
    "mem_mode": "internal_decoupled",
    "runtime_writeable_weights": 0,
    "inFIFODepths": [
      2
    ],
    "outFIFODepths": [
      2
    ],
    "slr": -1
  },
  "Thresholding_rtl_80": {
    "PE": 1,
    "runtime_writeable_weights": 0,
    "depth_trigger_uram": 0,
    "depth_trigger_bram": 0,
    "inFIFODepths": [
      2
    ],
    "outFIFODepths": [
      2
    ],
    "slr": -1
  },
  "AddStreams_hls_15": {
    "PE": 1,
    "inFIFODepths": [
      2,
      2
    ],
    "outFIFODepths": [
      2
    ],
    "slr": -1
  },
  "Thresholding_rtl_81": {
    "PE": 1,
    "runtime_writeable_weights": 0,
    "depth_trigger_uram": 0,
    "depth_trigger_bram": 0,
    "inFIFODepths": [
      2
    ],
    "outFIFODepths": [
      2
    ],
    "slr": -1
  },
  "GlobalAccPool_hls_0": {
    "PE": 1,
    "inFIFODepths": [
      2
    ],
    "outFIFODepths": [
      2
    ],
    "slr": -1
  },
  "Thresholding_rtl_82": {
    "PE": 1,
    "runtime_writeable_weights": 0,
    "depth_trigger_uram": 0,
    "depth_trigger_bram": 0,
    "inFIFODepths": [
      2
    ],
    "outFIFODepths": [
      2
    ],
    "slr": -1
  },
  "MVAU_hls_52": {
    "PE": 1,
    "SIMD": 1,
    "ram_style": "auto",
    "resType": "auto",
    "mem_mode": "internal_decoupled",
    "runtime_writeable_weights": 0,
    "inFIFODepths": [
      2
    ],
    "outFIFODepths": [
      2
    ],
    "slr": -1
  },
  "LabelSelect_hls_0": {
    "PE": 1,
    "inFIFODepths": [
      2
    ],
    "outFIFODepths": [
      2
    ],
    "slr": -1
  }
}